<?xml version="1.0" encoding="UTF-8"?>
<!DOCTYPE mapper PUBLIC "-//mybatis.org//DTD Mapper 3.0//EN" "http://mybatis.org/dtd/mybatis-3-mapper.dtd">
<mapper namespace="com.sales.dao.business.ActRangeMapper">
  <resultMap id="BaseResultMap" type="com.sales.model.business.ActRange">
    <!--
      WARNING - @mbg.generated
      This element is automatically generated by MyBatis Generator, do not modify.
    -->
    
    	<!-- // 主键 -->
    	<id column="id" property="id" />
    	<!-- // 活动编号 -->
		<result column="act_id" property="actId" />
    	<!-- // 关联产品编号(优惠套装-关联商品编号) -->
		<result column="material_id" property="materialId" />
    	<!-- // 关联品牌 -->
		<result column="brand_id" property="brandId" />
    	<!-- // 关联产品分类 -->
		<result column="mat_type_id" property="matTypeId" />
    	<!-- // 数量 -->
		<result column="quantity" property="quantity" />
    	<!-- // 关联活动规则 -->
		<result column="rule_id" property="ruleId" />
    
    <association property="actIdRef" javaType="com.sales.model.business.Activity">
    	<id column="act_id" property="id"/>
    	<result column="actIdRef_id" property="id" />
    	<result column="actIdRef_name" property="name" />
    </association>
    
    <association property="materialIdRef" javaType="com.sales.model.business.DrpMaterial">
    	<id column="material_id" property="id"/>
    	<result column="materialIdRef_id" property="id" />
    	<result column="materialIdRef_name" property="name" />
    </association>
    
    <association property="brandIdRef" javaType="com.sales.model.business.DrpBrand">
    	<id column="brand_id" property="id"/>
    	<result column="brandIdRef_id" property="id" />
    	<result column="brandIdRef_name" property="name" />
    </association>
    
    <association property="matTypeIdRef" javaType="com.sales.model.business.DrpMatType">
    	<id column="mat_type_id" property="id"/>
    	<result column="matTypeIdRef_id" property="id" />
    	<result column="matTypeIdRef_name" property="name" />
    </association>
    
    <association property="ruleIdRef" javaType="com.sales.model.business.ActRule">
    	<id column="rule_id" property="id"/>
    	<result column="ruleIdRef_id" property="id" />
    	<result column="ruleIdRef_name" property="name" />
    </association>
    
    
  </resultMap>
  
  <sql id="Base_Column_List">
    <!--
      WARNING - @mbg.generated
      This element is automatically generated by MyBatis Generator, do not modify.
    -->
    
    	o.id, 
    	actIdRef.id AS actIdRef_id, 
		actIdRef.name as actIdRef_name,
    	o.act_id, 
    	materialIdRef.id AS materialIdRef_id, 
		materialIdRef.name as materialIdRef_name,
    	o.material_id, 
    	brandIdRef.id AS brandIdRef_id, 
		brandIdRef.name as brandIdRef_name,
    	o.brand_id, 
    	matTypeIdRef.id AS matTypeIdRef_id, 
		matTypeIdRef.name as matTypeIdRef_name,
    	o.mat_type_id, 
    	o.quantity, 
    	ruleIdRef.id AS ruleIdRef_id, 
		ruleIdRef.name as ruleIdRef_name,
    	o.rule_id
	
  </sql>
  
  <sql id="Base_From_Tbl">
  	from t_act_range o
	    LEFT JOIN t_activity actIdRef ON (o.act_id = actIdRef.id)
	    LEFT JOIN t_drp_material materialIdRef ON (o.material_id = materialIdRef.id)
	    LEFT JOIN t_drp_brand brandIdRef ON (o.brand_id = brandIdRef.id)
	    LEFT JOIN t_drp_mat_type matTypeIdRef ON (o.mat_type_id = matTypeIdRef.id)
	    LEFT JOIN t_act_rule ruleIdRef ON (o.rule_id = ruleIdRef.id)
  </sql>
  
  <select id="selectByPrimaryKey" parameterType="java.lang.Long" resultMap="BaseResultMap">
    <!--
      WARNING - @mbg.generated
      This element is automatically generated by MyBatis Generator, do not modify.
    -->
    select 
    <include refid="Base_Column_List" />
    <include refid="Base_From_Tbl" />
    where o.id = #{id}
  </select>
  
  <delete id="deleteByPrimaryKey" parameterType="java.lang.Long">
    <!--
      WARNING - @mbg.generated
      This element is automatically generated by MyBatis Generator, do not modify.
    -->
    delete from t_act_range
    where id = #{id}
  </delete>
  
  <insert id="insert" parameterType="com.sales.model.business.ActRange">
    <!--
      WARNING - @mbg.generated
      This element is automatically generated by MyBatis Generator, do not modify.
    -->
    insert into t_act_range (
      id, 
      act_id, 
      material_id, 
      brand_id, 
      mat_type_id, 
      quantity, 
      rule_id
      )
    values (
      #{id}, 
      #{actId}, 
      #{materialId}, 
      #{brandId}, 
      #{matTypeId}, 
      #{quantity}, 
      #{ruleId}
      )
  </insert>
  
  <insert id="insertSelective" parameterType="com.sales.model.business.ActRange">
    <!--
      WARNING - @mbg.generated
      This element is automatically generated by MyBatis Generator, do not modify.
    -->
    insert into t_act_range
    <trim prefix="(" suffix=")" suffixOverrides=",">
      <if test="id != null">
        id,
      </if>
      <if test="actId != null">
        act_id,
      </if>
      <if test="materialId != null">
        material_id,
      </if>
      <if test="brandId != null">
        brand_id,
      </if>
      <if test="matTypeId != null">
        mat_type_id,
      </if>
      <if test="quantity != null">
        quantity,
      </if>
      <if test="ruleId != null">
        rule_id,
      </if>
    </trim>
    <trim prefix="values (" suffix=")" suffixOverrides=",">
      <if test="id != null">
        #{id},
      </if>
      <if test="actId != null">
        #{actId},
      </if>
      <if test="materialId != null">
        #{materialId},
      </if>
      <if test="brandId != null">
        #{brandId},
      </if>
      <if test="matTypeId != null">
        #{matTypeId},
      </if>
      <if test="quantity != null">
        #{quantity},
      </if>
      <if test="ruleId != null">
        #{ruleId},
      </if>
    </trim>
  </insert>
  
  <update id="updateByPrimaryKeySelective" parameterType="com.sales.model.business.ActRange">
    <!--
      WARNING - @mbg.generated
      This element is automatically generated by MyBatis Generator, do not modify.
    -->
    update t_act_range
    <set>
      <if test="id != null">
      	id = #{id},
      </if>
      <if test="actId != null">
      	act_id = #{actId},
      </if>
      <if test="materialId != null">
      	material_id = #{materialId},
      </if>
      <if test="brandId != null">
      	brand_id = #{brandId},
      </if>
      <if test="matTypeId != null">
      	mat_type_id = #{matTypeId},
      </if>
      <if test="quantity != null">
      	quantity = #{quantity},
      </if>
      <if test="ruleId != null">
      	rule_id = #{ruleId},
      </if>
    </set>
    where id = #{id}
  </update>
  
  <update id="updateByPrimaryKey" parameterType="com.sales.model.business.ActRange">
    <!--
      WARNING - @mbg.generated
      This element is automatically generated by MyBatis Generator, do not modify.
    -->
    update t_act_range
    set 
      id = #{id}, 
      act_id = #{actId}, 
      material_id = #{materialId}, 
      brand_id = #{brandId}, 
      mat_type_id = #{matTypeId}, 
      quantity = #{quantity}, 
      rule_id = #{ruleId}
    where id = #{id}
  </update>
  
  <select id="selectList" resultMap="BaseResultMap"
		parameterType="java.util.Map">
		<!-- WARNING - @mbggenerated This element is automatically generated by 
			MyBatis Generator, do not modify. -->
		select
		<include refid="Base_Column_List" />
		<include refid="Base_From_Tbl" />
		<where>
			
			<if test="model.id != null">
				<trim prefix="AND (" suffix=")" suffixOverrides="AND | OR">
					o.id = #{model.id}
				</trim>
			</if>
			
			<if test="model.actId != null">
				<trim prefix="AND (" suffix=")" suffixOverrides="AND | OR">
					o.act_id = #{model.actId}
				</trim>
			</if>
			
			<if test="model.materialId != null">
				<trim prefix="AND (" suffix=")" suffixOverrides="AND | OR">
					o.material_id = #{model.materialId}
				</trim>
			</if>
			
			<if test="model.brandId != null">
				<trim prefix="AND (" suffix=")" suffixOverrides="AND | OR">
					o.brand_id = #{model.brandId}
				</trim>
			</if>
			
			<if test="model.matTypeId != null">
				<trim prefix="AND (" suffix=")" suffixOverrides="AND | OR">
					o.mat_type_id = #{model.matTypeId}
				</trim>
			</if>
			
			<if test="model.quantity != null">
				<trim prefix="AND (" suffix=")" suffixOverrides="AND | OR">
					o.quantity = #{model.quantity}
				</trim>
			</if>
			
			<if test="model.ruleId != null">
				<trim prefix="AND (" suffix=")" suffixOverrides="AND | OR">
					o.rule_id = #{model.ruleId}
				</trim>
			</if>
		</where>
	</select>
	
</mapper>